dicedb/__init__.py
dicedb/commands.py
dicedb/const.py
dicedb/dice.py
dicedb/exceptions.py
dicedb/proto/__init__.py
dicedb/proto/cmd_pb2.py
dicedb/proto/cmd_pb2.pyi
dicedb/proto/res_pb2.py
dicedb/proto/res_pb2.pyi
dicedb/utils/__init__.py
dicedb/utils/response_deserializer.py
dicedb-0.1.1.dist-info/METADATA
dicedb-0.1.1.dist-info/WHEEL
dicedb-0.1.1.dist-info/RECORD
