Metadata-Version: 2.4
Name: dicedb
Version: 0.1.1
Summary: A simple DiceDB client for Python
Author-email: un4gt <mt3085570450@outlook.com>
Requires-Python: >=3.8
Requires-Dist: protobuf>=5.29.4
